django_triflesoft_certificate_auth-0.1.1509191803.dist-info/RECORD
django_triflesoft_certificate_auth-0.1.1509191803.dist-info/WHEEL
django_triflesoft_certificate_auth-0.1.1509191803.dist-info/DESCRIPTION.rst
django_triflesoft_certificate_auth-0.1.1509191803.dist-info/top_level.txt
django_triflesoft_certificate_auth-0.1.1509191803.dist-info/METADATA
django_triflesoft_certificate_auth-0.1.1509191803.dist-info/metadata.json
certificate_auth/middleware.py
certificate_auth/__init__.py
