Metadata-Version: 2.0
Name: django-triflesoft-certificate-auth
Version: 0.1.1509191803
Summary: Django certificate authentication by TrifleSoft
Home-page: https://bitbucket.org/triflesoft/django-certificate-auth
Author: TrifleSoft LLC
Author-email: support@triflesoft.org
License: BSD
Keywords: django certificate authentication triflesoft
Platform: UNKNOWN
Classifier: Development Status :: 5 - Production/Stable
Classifier: Environment :: No Input/Output (Daemon)
Classifier: Framework :: Django
Classifier: Framework :: Django :: 1.7
Classifier: Intended Audience :: Developers
Classifier: License :: OSI Approved :: BSD License
Classifier: Operating System :: POSIX :: Linux
Classifier: Programming Language :: Python :: 3 :: Only
Classifier: Programming Language :: Python :: 3.4
Requires-Dist: django
